[
  { "sl":"1",  "word":"بَلَى",     "en-sound":"balaa",     "bn-sound":"বালা" },
  { "sl":"2",  "word":"عَلَى",     "en-sound":"'alaa",     "bn-sound":"’আলা" },
  { "sl":"3",  "word":"كَفَى",     "en-sound":"kafaa",     "bn-sound":"কাফা" },
  { "sl":"4",  "word":"عَسَى",     "en-sound":"'asaa",     "bn-sound":"’আসা" },
  { "sl":"5",  "word":"سَعَى",     "en-sound":"sa'aa",     "bn-sound":"সা’আ" },
  { "sl":"6",  "word":"يَرَى",     "en-sound":"yaraa",     "bn-sound":"ইয়ার" },

  { "sl":"7",  "word":"إِلَى",     "en-sound":"ilaa",      "bn-sound":"ইলা" },
  { "sl":"8",  "word":"بِهِ",      "en-sound":"bihi",      "bn-sound":"বিহি" },
  { "sl":"9",  "word":"لَهُ",      "en-sound":"lahu",      "bn-sound":"লাহু" },
  { "sl":"10", "word":"أَوَى",     "en-sound":"a'waa",     "bn-sound":"আ’ওয়া" },
  { "sl":"11", "word":"طَغَى",     "en-sound":"taghaa",    "bn-sound":"তাগ" },
  { "sl":"12", "word":"ذٰلِكَ",    "en-sound":"dhaalika",  "bn-sound":"যালিকা" },

  { "sl":"13", "word":"أَحْوَى",   "en-sound":"a'hwaa",    "bn-sound":"আ’হওয়া" },
  { "sl":"14", "word":"تَرْضَى",   "en-sound":"tardaa",    "bn-sound":"তার্দ্ব" },
  { "sl":"15", "word":"أَغْنَى",   "en-sound":"a'ghnaa",   "bn-sound":"আ’গনা" },
  { "sl":"16", "word":"يَخْشَى",   "en-sound":"yakhshaa",  "bn-sound":"ইয়াখশা" },
  { "sl":"17", "word":"عِيسَى",    "en-sound":"'eesaa",    "bn-sound":"’ঈসা" },
  { "sl":"18", "word":"مُوسَى",    "en-sound":"muusaa",    "bn-sound":"মূসা" },

  { "sl":"19", "word":"أَوْحَى",   "en-sound":"awhaa",     "bn-sound":"আওহা" },
  { "sl":"20", "word":"يُتْلَى",   "en-sound":"yutlaa",    "bn-sound":"ইয়ুতলা" },
  { "sl":"21", "word":"وَثُقَ",    "en-sound":"wathuqa",   "bn-sound":"ওয়াছুকা" },
  { "sl":"22", "word":"وَسْطَى",   "en-sound":"wastaa",    "bn-sound":"ওয়াস্ত্বা" },
  { "sl":"23", "word":"يُحْيِي",   "en-sound":"yuhyii",    "bn-sound":"ইউহইই" },
  { "sl":"24", "word":"يُغْنِي",   "en-sound":"yughnii",   "bn-sound":"ইউগনী" },

  { "sl":"25", "word":"قَوْلٌ",    "en-sound":"qawlun",    "bn-sound":"ক্বওলুন" },
  { "sl":"26", "word":"وَيْلٌ",    "en-sound":"waylun",    "bn-sound":"ওয়াইলুন" },
  { "sl":"27", "word":"عَيْنٌ",    "en-sound":"'aynun",    "bn-sound":"’আইনুন" },
  { "sl":"28", "word":"خَيْرٌ",    "en-sound":"khayrun",   "bn-sound":"খইরুন" },
  { "sl":"29", "word":"خَوْفًا",   "en-sound":"khawfan",   "bn-sound":"খওফান" },
  { "sl":"30", "word":"طَيْرًا",   "en-sound":"tayran",    "bn-sound":"তাইরান" },

  { "sl":"31", "word":"كِتَابًا",  "en-sound":"kitaaban",  "bn-sound":"কিতাবান" },
  { "sl":"32", "word":"مَآبًا",    "en-sound":"maaban",    "bn-sound":"মাবান" },
  { "sl":"33", "word":"لِبَاسًا",  "en-sound":"libaasan",  "bn-sound":"লিবাসান" },
  { "sl":"34", "word":"حِسَابًا",  "en-sound":"hisaaban",  "bn-sound":"হিসাবান" },
  { "sl":"35", "word":"كَرَامًا",  "en-sound":"karaaman",  "bn-sound":"কারামান" },
  { "sl":"36", "word":"صَوَابًا",  "en-sound":"sawaaban",  "bn-sound":"সোয়াবান" },

  { "sl":"37", "word":"أَبْقَى",   "en-sound":"a'bqaa",    "bn-sound":"আ’বকা" },
  { "sl":"38", "word":"تَنْسَى",   "en-sound":"tansaa",    "bn-sound":"তানসা" },
  { "sl":"39", "word":"يَخْشَى",   "en-sound":"yakhshaa",  "bn-sound":"ইয়াখশা" },
  { "sl":"40", "word":"تَرْضَى",   "en-sound":"tardaa",    "bn-sound":"তার্দ্ব" },
  { "sl":"41", "word":"أَدْنَى",   "en-sound":"a'dnaa",    "bn-sound":"আ’দনা" },
  { "sl":"42", "word":"يَسْعَى",   "en-sound":"yas'aa",    "bn-sound":"ইয়াস’আ" },

  { "sl":"43", "word":"تَجْرِي",   "en-sound":"tajree",    "bn-sound":"তাজরী" },
  { "sl":"44", "word":"أَمْرِي",   "en-sound":"a'mree",    "bn-sound":"আ’ম্রী" },
  { "sl":"45", "word":"أَهْلِي",   "en-sound":"a'hlee",    "bn-sound":"আ’হলী" },
  { "sl":"46", "word":"يَهْدِي",   "en-sound":"yahdee",    "bn-sound":"ইয়াহদী" },
  { "sl":"47", "word":"يُغْنِي",   "en-sound":"yughnii",   "bn-sound":"ইউগনী" },
  { "sl":"48", "word":"يَبْقَى",   "en-sound":"yabqaa",    "bn-sound":"ইয়াবকা" },

  { "sl":"49", "word":"يَدْعُوا",  "en-sound":"yad'uu",    "bn-sound":"ইয়াদ’উ" },
  { "sl":"50", "word":"يَتْلُوا",  "en-sound":"yatluu",    "bn-sound":"ইয়াতলূ" },
  { "sl":"51", "word":"اُدْعُوا",  "en-sound":"ud'uu",     "bn-sound":"উদ’উ" },
  { "sl":"52", "word":"وَاعْفُوا", "en-sound":"wa'fuu",    "bn-sound":"ওয়া’ফূ" },
  { "sl":"53", "word":"يَرْمُوا",  "en-sound":"yarmuu",    "bn-sound":"ইয়ারমূ" },
  { "sl":"54", "word":"اَخْلَصُوا","en-sound":"akhlasuu", "bn-sound":"আখলাসূ" },

  { "sl":"55", "word":"بَصِيرًا",  "en-sound":"baseeran",  "bn-sound":"বাসীরন" },
  { "sl":"56", "word":"كَرِيمًا",  "en-sound":"kareeman",  "bn-sound":"কারীমান" },
  { "sl":"57", "word":"خَبِيرًا",  "en-sound":"khabeeran","bn-sound":"খবীরন" },
  { "sl":"58", "word":"نَعِيمًا",  "en-sound":"na'eeman", "bn-sound":"না’ঈমান" },
  { "sl":"59", "word":"ضَعِيفًا",  "en-sound":"da'eefan", "bn-sound":"দ্বঈফান" },
  { "sl":"60", "word":"عَلِيمًا",  "en-sound":"'aleeman", "bn-sound":"’আলীমান" }
]